pgai/__init__.py
pgai/__main__.py
pgai/cli.py
pgai/py.typed
pgai/tracing.py
pgai/_install/__init__.py
pgai/_install/install.py
pgai/alembic/__init__.py
pgai/alembic/operations.py
pgai/data/ai.sql
pgai/semantic_catalog/__init__.py
pgai/semantic_catalog/describe.py
pgai/semantic_catalog/exceptions.py
pgai/semantic_catalog/file.py
pgai/semantic_catalog/fix.py
pgai/semantic_catalog/gen_sql.py
pgai/semantic_catalog/loader.py
pgai/semantic_catalog/models.py
pgai/semantic_catalog/render.py
pgai/semantic_catalog/sample.py
pgai/semantic_catalog/search.py
pgai/semantic_catalog/semantic_catalog.py
pgai/semantic_catalog/templates/__init__.py
pgai/semantic_catalog/templates/templates/fact.j2
pgai/semantic_catalog/templates/templates/procedure.j2
pgai/semantic_catalog/templates/templates/prompt_gen_sql_system.j2
pgai/semantic_catalog/templates/templates/prompt_gen_sql_user.j2
pgai/semantic_catalog/templates/templates/sql_example.j2
pgai/semantic_catalog/templates/templates/table.j2
pgai/semantic_catalog/templates/templates/view.j2
pgai/semantic_catalog/vectorizer/__init__.py
pgai/semantic_catalog/vectorizer/models.py
pgai/semantic_catalog/vectorizer/ollama.py
pgai/semantic_catalog/vectorizer/openai.py
pgai/semantic_catalog/vectorizer/sentence_tranformers.py
pgai/semantic_catalog/vectorizer/vectorizer.py
pgai/sqlalchemy/__init__.py
pgai/vectorizer/__init__.py
pgai/vectorizer/chunking.py
pgai/vectorizer/configuration.py
pgai/vectorizer/create_vectorizer.py
pgai/vectorizer/db.py
pgai/vectorizer/destination.py
pgai/vectorizer/embeddings.py
pgai/vectorizer/formatting.py
pgai/vectorizer/loading.py
pgai/vectorizer/parsing.py
pgai/vectorizer/processing.py
pgai/vectorizer/vectorizer.py
pgai/vectorizer/worker.py
pgai/vectorizer/embedders/__init__.py
pgai/vectorizer/embedders/litellm.py
pgai/vectorizer/embedders/ollama.py
pgai/vectorizer/embedders/openai.py
pgai/vectorizer/embedders/voyageai.py
pgai/vectorizer/features/__init__.py
pgai/vectorizer/features/features.py
pgai-0.12.1.dist-info/METADATA
pgai-0.12.1.dist-info/WHEEL
pgai-0.12.1.dist-info/entry_points.txt
pgai-0.12.1.dist-info/licenses/LICENSE
pgai-0.12.1.dist-info/RECORD
