Metadata-Version: 2.4
Name: pgai
Version: 0.12.1
Summary: AI workflows in your PostgreSQL database
Project-URL: Homepage, https://github.com/timescale/pgai
Project-URL: Repository, https://github.com/timescale/pgai
Project-URL: Bug Tracker, https://github.com/timescale/pgai/issues
Project-URL: Documentation, https://github.com/timescale/pgai/tree/main/docs
License-File: LICENSE
Keywords: ai,postgres
Classifier: Intended Audience :: Developers
Classifier: License :: OSI Approved :: PostgreSQL License
Classifier: Operating System :: MacOS
Classifier: Operating System :: OS Independent
Classifier: Operating System :: POSIX
Classifier: Operating System :: POSIX :: Linux
Classifier: Programming Language :: Python :: 3
Classifier: Programming Language :: Python :: 3.10
Classifier: Programming Language :: Python :: 3.11
Classifier: Programming Language :: Python :: 3.12
Classifier: Programming Language :: Python :: 3.13
Classifier: Topic :: Database
Classifier: Topic :: Scientific/Engineering :: Artificial Intelligence
Classifier: Typing :: Typed
Requires-Python: >=3.10
Requires-Dist: click<9.0,>=8.0
Requires-Dist: datadog-lambda<7.0,>=6.9
Requires-Dist: psycopg[binary]<4.0,>=3.2
Requires-Dist: pydantic<3.0,>=2.0
Requires-Dist: python-dotenv<2.0,>=1.0
Requires-Dist: pytimeparse<2.0,>=1.1
Requires-Dist: semver>=3.0.4
Requires-Dist: structlog<26.0,>=24.0
Requires-Dist: typing-extensions<5.0,>=4.0
Provides-Extra: semantic-catalog
Requires-Dist: einops>=0.8.1; extra == 'semantic-catalog'
Requires-Dist: jinja2>=3.1.5; extra == 'semantic-catalog'
Requires-Dist: ollama<0.6.0,>=0.4.5; extra == 'semantic-catalog'
Requires-Dist: openai<2.0,>=1.44; extra == 'semantic-catalog'
Requires-Dist: pgvector<1.0,>=0.3; extra == 'semantic-catalog'
Requires-Dist: pydantic-ai>=0.2.12; extra == 'semantic-catalog'
Requires-Dist: pyyaml>=6.0.2; extra == 'semantic-catalog'
Requires-Dist: rich>=13.9.4; extra == 'semantic-catalog'
Requires-Dist: sentence-transformers>=4.0.2; extra == 'semantic-catalog'
Requires-Dist: torch>=2.6.0; extra == 'semantic-catalog'
Provides-Extra: sqlalchemy
Requires-Dist: alembic>=1.14.0; extra == 'sqlalchemy'
Requires-Dist: sqlalchemy>=2.0.36; extra == 'sqlalchemy'
Provides-Extra: vectorizer-worker
Requires-Dist: boto3-stubs[s3,sts]>=1.37.30; extra == 'vectorizer-worker'
Requires-Dist: boto3<2.0,>=1.35.0; extra == 'vectorizer-worker'
Requires-Dist: docling==2.34.0; extra == 'vectorizer-worker'
Requires-Dist: exceptiongroup<2.0,>=1.0; extra == 'vectorizer-worker'
Requires-Dist: filetype==1.2.0; extra == 'vectorizer-worker'
Requires-Dist: google-cloud-aiplatform[tokenization]<2.0,>=1.78.0; extra == 'vectorizer-worker'
Requires-Dist: ijson>=3.3.0; extra == 'vectorizer-worker'
Requires-Dist: langchain-text-splitters<1.0,>=0.2; extra == 'vectorizer-worker'
Requires-Dist: litellm<1.73.0,>=1.65.0; extra == 'vectorizer-worker'
Requires-Dist: mistral-common<2.0,>=1.0; extra == 'vectorizer-worker'
Requires-Dist: ollama<0.6.0,>=0.4.5; extra == 'vectorizer-worker'
Requires-Dist: openai<2.0,>=1.44; extra == 'vectorizer-worker'
Requires-Dist: pgvector<1.0,>=0.3; extra == 'vectorizer-worker'
Requires-Dist: pymupdf4llm==0.0.24; extra == 'vectorizer-worker'
Requires-Dist: smart-open==7.1.0; extra == 'vectorizer-worker'
Requires-Dist: tiktoken<1.0,>=0.7; extra == 'vectorizer-worker'
Requires-Dist: voyageai<0.3.2,>=0.3.1; (python_version < '3.13') and extra == 'vectorizer-worker'
